Workbook

Sheet income sheet tutorial

Sheet Income Sheet
B1: FY 2021 | C1: FY 2022 | D1: FY 2023 | E1: FY 2024 | F1: FY 2025 | G1: FY 2026E | H1: FY 2027E
A2: Revenue (thousands) | D2: 531109 | E2: 748024 | F2: 1037589 | G2: =F2*(1+Assumptions!B2) -> 1328113.9 | H2: =G2*(1+Assumptions!B3) -> 1620299
A3: Cost of Revenue | D3: 142105 | E3: 203645 | F3: 288132 | G3: =F3/F2*G2 -> 368808.96 | H3: =G3/G2*H2 -> 449946.93
A4: Gross Profit | D4: =D2-D3 -> 389004 | E4: =E2-E3 -> 544379 | F4: =F2-F3 -> 749457 | G4: =G2-G3 -> 959304.96 | H4: =H2-H3 -> 1170352.1
A5: Gross Margin % | D5: =D4/D2 -> 0.73243722 | E5: =E4/E2 -> 0.72775606 | F5: =F4/F2 -> 0.72230623 | G5: =G4/G2 -> 0.72230623 | H5: =H4/H2 -> 0.72230623
A6: R&D Expense | D6: 194352 | E6: 235298 | F6: 306323 | G6: =F6/F2*G2 -> 392093.44 | H6: =G6/G2*H2 -> 478354
A7: S&M Expense | D7: 75788 | E7: 90494 | F7: 125677 | G7: =F7/F2*G2 -> 160866.56 | H7: =G7/G2*H2 -> 196257.2
A8: G&A Expense | D8: 132123 | E8: 155992 | F8: 181887 | G8: =F8/F2*G2 -> 232815.36 | H8: =G8/G2*H2 -> 284034.74
A9: Total OpEx | D9: 402263 | E9: 481784 | F9: 613887 | G9: =G6+G7+G8 -> 785775.36 | H9: =H6+H7+H8 -> 958645.94
A10: EBITDA | D10: =D12+D11 -> -6164 | E10: =E12+E11 -> 73449 | F10: =F12+F11 -> 149961 | G10: =G12+G11 -> 191950.08 | H10: =H12+H11 -> 234179.1
A11: D&A | D11: 7095 | E11: 10854 | F11: 14391 | G11: =F11/F2*G2 -> 18420.48 | H11: =G11/G2*H2 -> 22472.986
A12: EBIT | D12: =D4-D9 -> -13259 | E12: =E4-E9 -> 62595 | F12: =F4-F9 -> 135570 | G12: =G4-G9 -> 173529.6 | H12: =H4-H9 -> 211706.11
A13: Pre-tax Income | D13: 17777 | E13: 102306 | F13: 182410 | G13: =G12+(F13-F12) -> 220369.6 | H13: =H12+(G13-G12) -> 258546.11
A14: Tax | D14: 2169 | E14: 13732 | F14: -231655 | G14: =G13*0.21 -> 46277.616 | H14: =H13*0.21 -> 54294.684
A15: Net Income | D15: 16067 | E15: 88574 | F15: 414065 | G15: =G13-G14 -> 174091.98 | H15: =H13-H14 -> 204251.43
A16: EPS | D16: 0.35 | E16: 1.88 | F16: 8.57 | G16: =G15/46000 -> 3.7846083 | H16: =H15/46000 -> 4.4402484

Sheet Balance Sheet

Sheet Cash Flow

Sheet DCF
B1: FY 2026E | C1: FY 2027E | D1: FY 2028E | F1: =B19 -> 72.417382 | G1: 0.08 | H1: 0.09 | I1: 0.1 | J1: 0.11 | K1: 0.12
A2: EBIT | B2: ='Income Sheet'!G12 -> 173529.6 | C2: ='Income Sheet'!H12 -> 211706.11 | D2: =C2*(1.18) -> 249813.21 | F2: 0.02 | G2: 85.898983 | H2: 76.588822 | I2: 69.610232 | J2: 64.185902 | K2: 59.849451
A3: Tax Rate | B3: 0.21 | C3: 0.21 | D3: 0.21 | F3: 0.025 | G3: 91.193676 | H3: 80.358792 | I3: 72.417382 | J3: 66.348097 | K3: 61.559634
A4: NOPAT | B4: =B2*(1-B3) -> 137088.38 | C4: =C2*(1-C3) -> 167247.83 | D4: =D2*(1-D3) -> 197352.44 | F4: 0.03 | G4: 97.547308 | H4: 84.75709 | I4: 75.625554 | J4: 68.780567 | K4: 63.459838
A5: D&A | B5: ='Income Sheet'!G11 -> 18420.48 | C5: ='Income Sheet'!H11 -> 22472.986 | D5: =C5*1.18 -> 26518.123 | F5: 0.035 | G5: 105.31286 | H5: 89.955079 | I5: 79.327291 | J5: 71.537366 | K5: 65.583595
A6: CapEx | B6: ='Income Sheet'!G2*0.017 -> 22577.937 | C6: ='Income Sheet'!H2*0.017 -> 27545.083 | D6: =C6*1.18 -> 32503.198
A7: Change in Working Capital | B7: 0 | C7: 0 | D7: 0 | F7: 0.1
A8: Free Cash Flow | B8: =B4+B5-B6-B7 -> 132930.93 | C8: =C4+C5-C6-C7 -> 162175.73 | D8: =D4+D5-D6-D7 -> 191367.36 | F8: 0.025
A9: Discount Factor | B9: =1/(1+$F$7)^1 -> 0.90909091 | C9: =1/(1+$F$7)^2 -> 0.82644628 | D9: =1/(1+$F$7)^3 -> 0.7513148
A10: PV of FCF | B10: =B8*B9 -> 120846.3 | C10: =C8*C9 -> 134029.53 | D10: =D8*D9 -> 143777.13
A12: Terminal Value | B12: =(D8*(1+$F$8))/($F$7-$F$8) -> 2615354
A13: PV of Terminal Value | B13: =B12*D9 -> 1964954.1
A14: Sum of PV FCFs | B14: =B10+C10+D10 -> 398652.96
A15: Enterprise Value | B15: =B13+B14 -> 2363607.1
A16: Less: Net Debt | B16: -1036389
A17: Equity Value | B17: =B15-B16 -> 3399996.1
A18: Shares Outstanding | B18: 46950
A19: Implied Share Price | B19: =B17/B18 -> 72.417382

Sheet Comps
A1: Company | B1: Ticker | C1: Market Cap | D1: Enterpise Value (EV) | E1: Revenue(NTM) | F1: EV/Revenue | G1: EV/EBITDA | H1: P/E | I1: Revenue Growth %
A2: Duolingo | B2: DUOL | C2: 6.16 | D2: 5 | E2: 1.1 | F2: 4.55 | G2: 28.17 | H2: 15.14 | I2: 0.39
A3: Spotify | B3: SPOT | C3: 93.66 | D3: 86.85 | E3: 20.21 | F3: 4.3 | G3: 30.8 | H3: 30.66 | I3: 0.0965
A4: Coursera | B4: COUR | C4: 1.74 | D4: 0.958 | E4: 0.7739 | F4: 1.24 | G4: n/a | H4: n/a | I4: 0.0904
A5: Snap | B5: SNAP | C5: 7.51 | D5: 8.89 | E5: 6.1 | F5: 1.46 | G5: n/a | H5: n/a | I5: 0.1026
A6: Pinterest | B6: PINS | C6: 11.12 | D6: 11.11 | E6: 4.37 | F6: 2.54 | G6: 31.83 | H6: 39.42 | I6: 0.163
F7: =MEDIAN(F2:F6) -> 2.54 | G7: =MEDIAN(G2:G6) -> 30.8 | H7: =MEDIAN(H2:H6) -> 30.66 | I7: =MEDIAN(I2:I6) -> 0.1026
F8: =AVERAGE(F2:F6) -> 2.818 | G8: =AVERAGE(G2:G6) -> 30.266667 | H8: =AVERAGE(H2:H6) -> 28.406667 | I8: =AVERAGE(I2:I6) -> 0.1685
A10: Comps-Implied Price
A11: =(G7*'Income Sheet'!G10 + 1036389)/46950 -> 147.99684

Sheet Assumptions
A1: Revenue Growth Y1 | B1: 0.39
A2: Revenue Growth Y2 | B2: 0.28
A3: Revenue Growth Y3 | B3: 0.22
A4: Gross Margin | B4: 0.73
A5: EBITDA Margin | B5: 0.21
A6: WACC | B6: 0.1
A7: Terminal Growth Rate | B7: 0.025
